<?xml version="1.0" encoding="utf-8"?>
<CoverageSession xmlns:xsd="http://www.w3.org/2001/XMLSchema" xmlns:xsi="http://www.w3.org/2001/XMLSchema-instance" Version="0.0.0.0">
  <Summary numSequencePoints="24" visitedSequencePoints="21" numBranchPoints="0" visitedBranchPoints="0" sequenceCoverage="87.50" branchCoverage="0.0" maxCyclomaticComplexity="0" minCyclomaticComplexity="0" maxCrapScore="0" minCrapScore="0" visitedClasses="2" numClasses="3" visitedMethods="5" numMethods="5" />
  <Modules>
    <Module>
      <Summary numSequencePoints="6" visitedSequencePoints="3" numBranchPoints="0" visitedBranchPoints="0" sequenceCoverage="50.00" branchCoverage="0.0" maxCyclomaticComplexity="0" minCyclomaticComplexity="0" maxCrapScore="0" minCrapScore="0" visitedClasses="1" numClasses="1" visitedMethods="1" numMethods="1" />
      <ModuleTime>0001-01-01T00:00:00</ModuleTime>
      <ModuleName>Scripts</ModuleName>
      <Files>
        <File uid="1" fullPath="C:/Users/kevin/OneDrive/Desktop/UNO/UNO-Flip-3D/UNOFlip/Assets/Scripts/AiPlayer.cs" />
        <File uid="2" fullPath="C:/Users/kevin/OneDrive/Desktop/UNO/UNO-Flip-3D/UNOFlip/Assets/Scripts/Card.cs" />
        <File uid="3" fullPath="C:/Users/kevin/OneDrive/Desktop/UNO/UNO-Flip-3D/UNOFlip/Assets/Scripts/CardDisplay.cs" />
        <File uid="4" fullPath="C:/Users/kevin/OneDrive/Desktop/UNO/UNO-Flip-3D/UNOFlip/Assets/Scripts/CardInteraction.cs" />
        <File uid="5" fullPath="C:/Users/kevin/OneDrive/Desktop/UNO/UNO-Flip-3D/UNOFlip/Assets/Scripts/Deck.cs" />
        <File uid="6" fullPath="C:/Users/kevin/OneDrive/Desktop/UNO/UNO-Flip-3D/UNOFlip/Assets/Scripts/GameManager.cs" />
        <File uid="7" fullPath="C:/Users/kevin/OneDrive/Desktop/UNO/UNO-Flip-3D/UNOFlip/Assets/Scripts/Menu.cs" />
        <File uid="8" fullPath="C:/Users/kevin/OneDrive/Desktop/UNO/UNO-Flip-3D/UNOFlip/Assets/Scripts/Player.cs" />
        <File uid="9" fullPath="C:/Users/kevin/OneDrive/Desktop/UNO/UNO-Flip-3D/UNOFlip/Assets/Scripts/WildButton.cs" />
      </Files>
      <Classes>
        <Class>
          <Summary numSequencePoints="6" visitedSequencePoints="3" numBranchPoints="0" visitedBranchPoints="0" sequenceCoverage="50.00" branchCoverage="0.0" maxCyclomaticComplexity="0" minCyclomaticComplexity="0" maxCrapScore="0" minCrapScore="0" visitedClasses="1" numClasses="1" visitedMethods="1" numMethods="1" />
          <FullName>Menu</FullName>
          <Methods>
            <Method visited="true" cyclomaticComplexity="0" nPathComplexity="0" sequenceCoverage="50.00" branchCoverage="0" crapScore="0" isConstructor="false" isStatic="false" isGetter="false" isSetter="false">
              <Summary numSequencePoints="6" visitedSequencePoints="3" numBranchPoints="0" visitedBranchPoints="0" sequenceCoverage="50.00" branchCoverage="0" maxCyclomaticComplexity="0" minCyclomaticComplexity="0" maxCrapScore="0" minCrapScore="0" visitedClasses="0" numClasses="0" visitedMethods="1" numMethods="1" />
              <MetadataToken>100663361</MetadataToken>
              <Name>System.Void Menu::HowToPlayPanel()</Name>
              <FileRef uid="7" />
              <SequencePoints>
                <SequencePoint vc="1" uspid="104136" ordinal="0" offset="0" sl="16" sc="5" el="16" ec="5" bec="0" bev="0" fileid="7">
                  <TrackedMethodRefs>
                    <TrackedMethodRef uid="0" vc="1" />
                  </TrackedMethodRefs>
                </SequencePoint>
                <SequencePoint vc="1" uspid="104137" ordinal="0" offset="1" sl="17" sc="9" el="17" ec="9" bec="0" bev="0" fileid="7">
                  <TrackedMethodRefs>
                    <TrackedMethodRef uid="0" vc="1" />
                  </TrackedMethodRefs>
                </SequencePoint>
                <SequencePoint vc="0" uspid="104138" ordinal="0" offset="17" sl="18" sc="9" el="18" ec="9" bec="0" bev="0" fileid="7">
                  <TrackedMethodRefs>
                    <TrackedMethodRef uid="0" vc="0" />
                  </TrackedMethodRefs>
                </SequencePoint>
                <SequencePoint vc="0" uspid="104139" ordinal="0" offset="18" sl="19" sc="13" el="19" ec="13" bec="0" bev="0" fileid="7">
                  <TrackedMethodRefs>
                    <TrackedMethodRef uid="0" vc="0" />
                  </TrackedMethodRefs>
                </SequencePoint>
                <SequencePoint vc="0" uspid="104140" ordinal="0" offset="31" sl="20" sc="9" el="20" ec="9" bec="0" bev="0" fileid="7">
                  <TrackedMethodRefs>
                    <TrackedMethodRef uid="0" vc="0" />
                  </TrackedMethodRefs>
                </SequencePoint>
                <SequencePoint vc="1" uspid="104141" ordinal="0" offset="32" sl="21" sc="5" el="21" ec="5" bec="0" bev="0" fileid="7">
                  <TrackedMethodRefs>
                    <TrackedMethodRef uid="0" vc="1" />
                  </TrackedMethodRefs>
                </SequencePoint>
              </SequencePoints>
              <BranchPoints />
            </Method>
          </Methods>
        </Class>
      </Classes>
      <TrackedMethods>
        <TrackedMethod uid="0" token="100663377" name="System.Void MenuTests::Test_Menu_HowToPlayPanel_NullHandling()" strategy="Test" />
      </TrackedMethods>
    </Module>
    <Module>
      <Summary numSequencePoints="18" visitedSequencePoints="18" numBranchPoints="0" visitedBranchPoints="0" sequenceCoverage="100.0" branchCoverage="0.0" maxCyclomaticComplexity="0" minCyclomaticComplexity="0" maxCrapScore="0" minCrapScore="0" visitedClasses="1" numClasses="2" visitedMethods="4" numMethods="4" />
      <ModuleTime>0001-01-01T00:00:00</ModuleTime>
      <ModuleName>Tests</ModuleName>
      <Files>
        <File uid="10" fullPath="C:/Users/kevin/OneDrive/Desktop/UNO/UNO-Flip-3D/UNOFlip/Assets/Tests/AiPlayerTests.cs" />
        <File uid="11" fullPath="C:/Users/kevin/OneDrive/Desktop/UNO/UNO-Flip-3D/UNOFlip/Assets/Tests/CardDisplayTests.cs" />
        <File uid="12" fullPath="C:/Users/kevin/OneDrive/Desktop/UNO/UNO-Flip-3D/UNOFlip/Assets/Tests/CardInteractionTests.cs" />
        <File uid="13" fullPath="C:/Users/kevin/OneDrive/Desktop/UNO/UNO-Flip-3D/UNOFlip/Assets/Tests/CardTests.cs" />
        <File uid="14" fullPath="C:/Users/kevin/OneDrive/Desktop/UNO/UNO-Flip-3D/UNOFlip/Assets/Tests/DeckTests.cs" />
        <File uid="15" fullPath="C:/Users/kevin/OneDrive/Desktop/UNO/UNO-Flip-3D/UNOFlip/Assets/Tests/GameManagerTests.cs" />
        <File uid="16" fullPath="C:/Users/kevin/OneDrive/Desktop/UNO/UNO-Flip-3D/UNOFlip/Assets/Tests/MenuTests.cs" />
        <File uid="17" fullPath="C:/Users/kevin/OneDrive/Desktop/UNO/UNO-Flip-3D/UNOFlip/Assets/Tests/PlayerTests.cs" />
      </Files>
      <Classes>
        <Class>
          <Summary numSequencePoints="0" visitedSequencePoints="0" numBranchPoints="0" visitedBranchPoints="0" sequenceCoverage="0" branchCoverage="0" maxCyclomaticComplexity="0" minCyclomaticComplexity="0" maxCrapScore="0" minCrapScore="0" visitedClasses="0" numClasses="1" visitedMethods="0" numMethods="0" />
          <FullName>GameManagerTests</FullName>
          <Methods />
        </Class>
        <Class>
          <Summary numSequencePoints="18" visitedSequencePoints="18" numBranchPoints="0" visitedBranchPoints="0" sequenceCoverage="100.0" branchCoverage="0.0" maxCyclomaticComplexity="0" minCyclomaticComplexity="0" maxCrapScore="0" minCrapScore="0" visitedClasses="1" numClasses="1" visitedMethods="4" numMethods="4" />
          <FullName>MenuTests</FullName>
          <Methods>
            <Method visited="true" cyclomaticComplexity="0" nPathComplexity="0" sequenceCoverage="100.0" branchCoverage="0" crapScore="0" isConstructor="false" isStatic="false" isGetter="false" isSetter="false">
              <Summary numSequencePoints="8" visitedSequencePoints="8" numBranchPoints="0" visitedBranchPoints="0" sequenceCoverage="100.0" branchCoverage="0" maxCyclomaticComplexity="0" minCyclomaticComplexity="0" maxCrapScore="0" minCrapScore="0" visitedClasses="0" numClasses="0" visitedMethods="1" numMethods="1" />
              <MetadataToken>100663374</MetadataToken>
              <Name>System.Void MenuTests::SetUp()</Name>
              <FileRef uid="16" />
              <SequencePoints>
                <SequencePoint vc="1" uspid="105377" ordinal="0" offset="0" sl="38" sc="5" el="38" ec="5" bec="0" bev="0" fileid="16">
                  <TrackedMethodRefs>
                    <TrackedMethodRef uid="1" vc="1" />
                  </TrackedMethodRefs>
                </SequencePoint>
                <SequencePoint vc="1" uspid="105378" ordinal="0" offset="1" sl="40" sc="9" el="40" ec="9" bec="0" bev="0" fileid="16">
                  <TrackedMethodRefs>
                    <TrackedMethodRef uid="1" vc="1" />
                  </TrackedMethodRefs>
                </SequencePoint>
                <SequencePoint vc="1" uspid="105379" ordinal="0" offset="17" sl="41" sc="9" el="41" ec="9" bec="0" bev="0" fileid="16">
                  <TrackedMethodRefs>
                    <TrackedMethodRef uid="1" vc="1" />
                  </TrackedMethodRefs>
                </SequencePoint>
                <SequencePoint vc="1" uspid="105380" ordinal="0" offset="34" sl="44" sc="9" el="44" ec="9" bec="0" bev="0" fileid="16">
                  <TrackedMethodRefs>
                    <TrackedMethodRef uid="1" vc="1" />
                  </TrackedMethodRefs>
                </SequencePoint>
                <SequencePoint vc="1" uspid="105381" ordinal="0" offset="50" sl="45" sc="9" el="45" ec="9" bec="0" bev="0" fileid="16">
                  <TrackedMethodRefs>
                    <TrackedMethodRef uid="1" vc="1" />
                  </TrackedMethodRefs>
                </SequencePoint>
                <SequencePoint vc="1" uspid="105382" ordinal="0" offset="63" sl="48" sc="9" el="48" ec="9" bec="0" bev="0" fileid="16">
                  <TrackedMethodRefs>
                    <TrackedMethodRef uid="1" vc="1" />
                  </TrackedMethodRefs>
                </SequencePoint>
                <SequencePoint vc="1" uspid="105383" ordinal="0" offset="86" sl="49" sc="9" el="49" ec="9" bec="0" bev="0" fileid="16">
                  <TrackedMethodRefs>
                    <TrackedMethodRef uid="1" vc="1" />
                  </TrackedMethodRefs>
                </SequencePoint>
                <SequencePoint vc="1" uspid="105384" ordinal="0" offset="110" sl="50" sc="5" el="50" ec="5" bec="0" bev="0" fileid="16">
                  <TrackedMethodRefs>
                    <TrackedMethodRef uid="1" vc="1" />
                  </TrackedMethodRefs>
                </SequencePoint>
              </SequencePoints>
              <BranchPoints />
            </Method>
            <Method visited="true" cyclomaticComplexity="0" nPathComplexity="0" sequenceCoverage="100.0" branchCoverage="0" crapScore="0" isConstructor="false" isStatic="false" isGetter="false" isSetter="false">
              <Summary numSequencePoints="4" visitedSequencePoints="4" numBranchPoints="0" visitedBranchPoints="0" sequenceCoverage="100.0" branchCoverage="0" maxCyclomaticComplexity="0" minCyclomaticComplexity="0" maxCrapScore="0" minCrapScore="0" visitedClasses="0" numClasses="0" visitedMethods="1" numMethods="1" />
              <MetadataToken>100663375</MetadataToken>
              <Name>System.Void MenuTests::TearDown()</Name>
              <FileRef uid="16" />
              <SequencePoints>
                <SequencePoint vc="1" uspid="105385" ordinal="0" offset="0" sl="54" sc="5" el="54" ec="5" bec="0" bev="0" fileid="16">
                  <TrackedMethodRefs>
                    <TrackedMethodRef uid="1" vc="1" />
                  </TrackedMethodRefs>
                </SequencePoint>
                <SequencePoint vc="1" uspid="105386" ordinal="0" offset="1" sl="55" sc="9" el="55" ec="9" bec="0" bev="0" fileid="16">
                  <TrackedMethodRefs>
                    <TrackedMethodRef uid="1" vc="1" />
                  </TrackedMethodRefs>
                </SequencePoint>
                <SequencePoint vc="1" uspid="105387" ordinal="0" offset="13" sl="56" sc="9" el="56" ec="9" bec="0" bev="0" fileid="16">
                  <TrackedMethodRefs>
                    <TrackedMethodRef uid="1" vc="1" />
                  </TrackedMethodRefs>
                </SequencePoint>
                <SequencePoint vc="1" uspid="105388" ordinal="0" offset="25" sl="57" sc="5" el="57" ec="5" bec="0" bev="0" fileid="16">
                  <TrackedMethodRefs>
                    <TrackedMethodRef uid="1" vc="1" />
                  </TrackedMethodRefs>
                </SequencePoint>
              </SequencePoints>
              <BranchPoints />
            </Method>
            <Method visited="true" cyclomaticComplexity="0" nPathComplexity="0" sequenceCoverage="100.0" branchCoverage="0" crapScore="0" isConstructor="false" isStatic="false" isGetter="false" isSetter="false">
              <Summary numSequencePoints="5" visitedSequencePoints="5" numBranchPoints="0" visitedBranchPoints="0" sequenceCoverage="100.0" branchCoverage="0" maxCyclomaticComplexity="0" minCyclomaticComplexity="0" maxCrapScore="0" minCrapScore="0" visitedClasses="0" numClasses="0" visitedMethods="1" numMethods="1" />
              <MetadataToken>100663377</MetadataToken>
              <Name>System.Void MenuTests::Test_Menu_HowToPlayPanel_NullHandling()</Name>
              <FileRef uid="16" />
              <SequencePoints>
                <SequencePoint vc="1" uspid="105394" ordinal="0" offset="0" sl="71" sc="5" el="71" ec="5" bec="0" bev="0" fileid="16">
                  <TrackedMethodRefs>
                    <TrackedMethodRef uid="1" vc="1" />
                  </TrackedMethodRefs>
                </SequencePoint>
                <SequencePoint vc="1" uspid="105395" ordinal="0" offset="1" sl="73" sc="9" el="73" ec="9" bec="0" bev="0" fileid="16">
                  <TrackedMethodRefs>
                    <TrackedMethodRef uid="1" vc="1" />
                  </TrackedMethodRefs>
                </SequencePoint>
                <SequencePoint vc="1" uspid="105396" ordinal="0" offset="24" sl="74" sc="9" el="74" ec="9" bec="0" bev="0" fileid="16">
                  <TrackedMethodRefs>
                    <TrackedMethodRef uid="1" vc="1" />
                  </TrackedMethodRefs>
                </SequencePoint>
                <SequencePoint vc="1" uspid="105397" ordinal="0" offset="43" sl="77" sc="9" el="77" ec="9" bec="0" bev="0" fileid="16">
                  <TrackedMethodRefs>
                    <TrackedMethodRef uid="1" vc="1" />
                  </TrackedMethodRefs>
                </SequencePoint>
                <SequencePoint vc="1" uspid="105398" ordinal="0" offset="71" sl="78" sc="5" el="78" ec="5" bec="0" bev="0" fileid="16">
                  <TrackedMethodRefs>
                    <TrackedMethodRef uid="1" vc="1" />
                  </TrackedMethodRefs>
                </SequencePoint>
              </SequencePoints>
              <BranchPoints />
            </Method>
            <Method visited="true" cyclomaticComplexity="0" nPathComplexity="0" sequenceCoverage="100.0" branchCoverage="0" crapScore="0" isConstructor="false" isStatic="false" isGetter="false" isSetter="false">
              <Summary numSequencePoints="1" visitedSequencePoints="1" numBranchPoints="0" visitedBranchPoints="0" sequenceCoverage="100.0" branchCoverage="0" maxCyclomaticComplexity="0" minCyclomaticComplexity="0" maxCrapScore="0" minCrapScore="0" visitedClasses="0" numClasses="0" visitedMethods="1" numMethods="1" />
              <MetadataToken>100663382</MetadataToken>
              <Name>System.Void MenuTests::&lt;Test_Menu_HowToPlayPanel_NullHandling&gt;b__7_0()</Name>
              <FileRef uid="16" />
              <SequencePoints>
                <SequencePoint vc="1" uspid="105412" ordinal="0" offset="0" sl="77" sc="35" el="77" ec="35" bec="0" bev="0" fileid="16">
                  <TrackedMethodRefs>
                    <TrackedMethodRef uid="1" vc="1" />
                  </TrackedMethodRefs>
                </SequencePoint>
              </SequencePoints>
              <BranchPoints />
            </Method>
          </Methods>
        </Class>
      </Classes>
      <TrackedMethods>
        <TrackedMethod uid="1" token="100663377" name="System.Void MenuTests::Test_Menu_HowToPlayPanel_NullHandling()" strategy="Test" />
      </TrackedMethods>
    </Module>
  </Modules>
</CoverageSession>